radontea/__init__.py
radontea/_alg_art.py
radontea/_alg_bpj.py
radontea/_alg_fmp.py
radontea/_alg_int.py
radontea/_alg_sart.py
radontea/_rdn_fan.py
radontea/_rdn_prl.py
radontea/_threed.py
radontea/_version.py
radontea/fan.py
radontea/logo.py
radontea/util.py
radontea-0.5.2.dist-info/licenses/LICENSE
radontea-0.5.2.dist-info/METADATA
radontea-0.5.2.dist-info/WHEEL
radontea-0.5.2.dist-info/top_level.txt
radontea-0.5.2.dist-info/RECORD
