Metadata-Version: 2.4
Name: radontea
Version: 0.5.2
Summary: collection of algorithms to compute the inverse Radon transform
Author: Tim Hetkämper
Author-email: Paul Müller <dev@craban.de>
License: Copyright (c) 2014, Paul Müller
Project-URL: source, https://github.com/RI-imaging/radontea
Project-URL: tracker, https://github.com/RI-imaging/radontea/issues
Project-URL: documentation, https://radontea.readthedocs.io/en/stable/
Project-URL: changelog, https://radontea.readthedocs.io/en/stable/sec_changelog.html
Classifier: Operating System :: OS Independent
Classifier: Programming Language :: Python :: 3
Classifier: Intended Audience :: Science/Research
Requires-Python: <4,>=3.8
License-File: LICENSE
Requires-Dist: numpy>=1.5.1
Requires-Dist: scipy>=1.4.0
Dynamic: license-file
